{
    "created_time": "2021-02-19T03:14:48Z",
    "files": [
        {
            "attachment_folder": "",
            "attachments": [
            ],
            "created_time": "2021-02-19T03:14:48Z",
            "modified_time": "2021-02-19T03:14:48Z",
            "name": "1-低代码并不Low.md",
            "tags": [
            ]
        },
        {
            "attachment_folder": "",
            "attachments": [
            ],
            "created_time": "2021-02-19T03:14:48Z",
            "modified_time": "2021-02-19T03:14:48Z",
            "name": "2-小程序-用户争夺战的新战场.md",
            "tags": [
            ]
        },
        {
            "attachment_folder": "",
            "attachments": [
            ],
            "created_time": "2021-02-19T03:14:48Z",
            "modified_time": "2021-02-19T03:14:48Z",
            "name": "3-快应用.md",
            "tags": [
            ]
        },
        {
            "attachment_folder": "",
            "attachments": [
            ],
            "created_time": "2021-02-19T03:14:48Z",
            "modified_time": "2021-02-19T03:14:48Z",
            "name": "z.md",
            "tags": [
            ]
        },
        {
            "attachment_folder": "",
            "attachments": [
            ],
            "created_time": "2021-02-19T03:14:48Z",
            "modified_time": "2021-02-19T03:14:48Z",
            "name": "z的副本.md",
            "tags": [
            ]
        },
        {
            "attachment_folder": "",
            "attachments": [
            ],
            "created_time": "2021-02-19T03:14:48Z",
            "modified_time": "2021-02-19T03:14:48Z",
            "name": "z的副本2.md",
            "tags": [
            ]
        },
        {
            "attachment_folder": "",
            "attachments": [
            ],
            "created_time": "2021-02-19T03:14:48Z",
            "modified_time": "2021-02-19T03:14:48Z",
            "name": "z的副本3.md",
            "tags": [
            ]
        }
    ],
    "sub_directories": [
    ],
    "version": "1"
}
